gliner_cpp.cpython-311-x86_64-linux-musl.so
gliner_cpp.pyi
libonnxruntime.so
libonnxruntime.so.1
libonnxruntime.so.1.19.2
libonnxruntime_providers_shared.so
bin/pcre2-config
cmake/pcre2-config-version.cmake
cmake/pcre2-config.cmake
include/msgpack.hpp
include/pcre2.h
include/pcre2posix.h
include/msgpack/assert.hpp
include/msgpack/cpp_config.hpp
include/msgpack/cpp_config_decl.hpp
include/msgpack/cpp_version.hpp
include/msgpack/create_object_visitor.hpp
include/msgpack/create_object_visitor_decl.hpp
include/msgpack/fbuffer.hpp
include/msgpack/fbuffer_decl.hpp
include/msgpack/gcc_atomic.hpp
include/msgpack/iterator.hpp
include/msgpack/iterator_decl.hpp
include/msgpack/meta.hpp
include/msgpack/meta_decl.hpp
include/msgpack/null_visitor.hpp
include/msgpack/null_visitor_decl.hpp
include/msgpack/object.hpp
include/msgpack/object_decl.hpp
include/msgpack/object_fwd.hpp
include/msgpack/object_fwd_decl.hpp
include/msgpack/pack.hpp
include/msgpack/pack_decl.hpp
include/msgpack/parse.hpp
include/msgpack/parse_decl.hpp
include/msgpack/parse_return.hpp
include/msgpack/predef.h
include/msgpack/preprocessor.hpp
include/msgpack/sbuffer.hpp
include/msgpack/sbuffer_decl.hpp
include/msgpack/sysdep.hpp
include/msgpack/type.hpp
include/msgpack/unpack.hpp
include/msgpack/unpack_decl.hpp
include/msgpack/unpack_define.hpp
include/msgpack/unpack_exception.hpp
include/msgpack/version.hpp
include/msgpack/version_master.hpp
include/msgpack/versioning.hpp
include/msgpack/vrefbuffer.hpp
include/msgpack/vrefbuffer_decl.hpp
include/msgpack/x3_parse.hpp
include/msgpack/x3_parse_decl.hpp
include/msgpack/x3_unpack.hpp
include/msgpack/x3_unpack_decl.hpp
include/msgpack/zbuffer.hpp
include/msgpack/zbuffer_decl.hpp
include/msgpack/zone.hpp
include/msgpack/zone_decl.hpp
include/msgpack/adaptor/adaptor_base.hpp
include/msgpack/adaptor/adaptor_base_decl.hpp
include/msgpack/adaptor/array_ref.hpp
include/msgpack/adaptor/array_ref_decl.hpp
gliner_cpp-0.1.dist-info/METADATA
gliner_cpp-0.1.dist-info/WHEEL
gliner_cpp-0.1.dist-info/RECORD
gliner_cpp-0.1.dist-info/licenses/LICENSE
