Metadata-Version: 2.2
Name: gliner-cpp
Version: 0.1
Summary: Python bindings for the GLiNER C++ inference library
Author: GLiNER Contributors
License:                                  Apache License
Project-URL: Homepage, https://github.com/LemurPwned/GLiNER.cpp
Requires-Python: >=3.10
